discord_socket/__init__.py
discord_socket/cache.py
discord_socket/client.py
discord_socket/intents.py
discord_socket/parser.py
discord_socket/websocket.py
discord.socket-0.0.5.dist-info/LICENSE
discord.socket-0.0.5.dist-info/METADATA
discord.socket-0.0.5.dist-info/WHEEL
discord.socket-0.0.5.dist-info/top_level.txt
discord.socket-0.0.5.dist-info/RECORD
